swtor_settings_updater/__init__.py
swtor_settings_updater/character.py
swtor_settings_updater/chat.py
swtor_settings_updater/color.py
swtor_settings_updater/py.typed
swtor_settings_updater/util/__init__.py
swtor_settings_updater/util/character_class.py
swtor_settings_updater/util/option_transformer.py
swtor_settings_updater/util/settings_dir.py
swtor_settings_updater/util/swtor_case.py
swtor_settings_updater-0.0.7.dist-info/LICENSE
swtor_settings_updater-0.0.7.dist-info/WHEEL
swtor_settings_updater-0.0.7.dist-info/METADATA
swtor_settings_updater-0.0.7.dist-info/RECORD
