Metadata-Version: 2.1
Name: swtor-settings-updater
Version: 0.0.7
Summary: Star Wars: The Old Republic Settings Updater
Home-page: https://github.com/ion1/swtor-settings-updater
License: MIT
Author: Johan Kiviniemi
Author-email: devel@johan.kiviniemi.name
Requires-Python: >=3.10,<4.0
Classifier: Development Status :: 3 - Alpha
Classifier: License :: OSI Approved :: MIT License
Classifier: Operating System :: OS Independent
Classifier: Programming Language :: Python :: 3
Classifier: Programming Language :: Python :: 3.10
Classifier: Topic :: Utilities
Requires-Dist: atomicwrites (>=1.4.0,<2.0.0)
Requires-Dist: regex (>=2020.7.14)
